.gitignore
CMakeLists.txt
README.md
pyproject.toml
setup.py
_skbuild/macosx-13.0-x86_64-3.11/cmake-install/mq_sa/__init__.py
_skbuild/macosx-13.0-x86_64-3.11/cmake-install/mq_sa/_mq_sa.cpython-311-darwin.so
mq_sa/__init__.py
mq_sa/_mq_sa.cpp
mq_sa.egg-info/PKG-INFO
mq_sa.egg-info/SOURCES.txt
mq_sa.egg-info/dependency_links.txt
mq_sa.egg-info/top_level.txt