Metadata-Version: 2.1
Name: mq-sa
Version: 0.0.7
Summary: Message queue for Interprocess communication
Home-page: https://github.com/SmashingAlpha/message-queue
Author: Yakov Wildfluss <yakov@smashingalpha.com>
License: MIT
Requires-Python: >=3.7
